{
    "AXIS":                      1,
    "MICROSTEPS":                256,
    "ACCELERATION":              400,
    "DECELLERATION":             700,
    "INITIALVELOCITY":           300,
    "ENDVELOCITY":               800,
    "HOLDCURRENT":               10,
    "RUNCURRENT":                70,
    "HOMINGVELOCITY":            800,
    "MAX_HOMING_OVERSHOOT":      18000,
    "HOME_SWITCH":               "S2",
    "HOME_DIRECTION":            1,
    "IDLE_POSITION":             100,
    "CLOCKRATIO":                100,
    "CLOCKWIDTH":                10,
    "ENCODER":                   1,
    "STALLMODE":                 1,
    "STALLFACTOR":               20,
    "DEADBAND":                  1,
    "ENCODERLINE":               512,
    "POSITIONMAINTENANCE":       0,
    "COUNTER1":                  1000,
    "COUNTER2":                  0,
    "USER1":                     1,
    "HOMING_MOVEMENT_DIRECTION": 1
}
